imageflow/__init__.py
imageflow/convert_to_records.py
imageflow/imageflow.py
imageflow/playground.py
imageflow/reader.py
imageflow/utils.py
imageflow-0.0.2.dist-info/DESCRIPTION.rst
imageflow-0.0.2.dist-info/METADATA
imageflow-0.0.2.dist-info/RECORD
imageflow-0.0.2.dist-info/WHEEL
imageflow-0.0.2.dist-info/metadata.json
imageflow-0.0.2.dist-info/top_level.txt
