Metadata-Version: 2.0
Name: imageflow
Version: 0.0.2
Summary: Import, Convert (and Soon Train) images with TensorFlow
Home-page: http://hamedmp.github.io/ImageFlow/
Author: Hamed Mohammadpour
Author-email: hamedmp@my.com
License: MIT
Keywords: tensorflow image cnn
Platform: UNKNOWN
Classifier: License :: OSI Approved :: MIT License
Classifier: Programming Language :: Python :: 2.7
Requires-Dist: numpy
Requires-Dist: pillow
